hashDecrypt.py
hashdecrypt-1.0.2.dist-info/WHEEL
hashdecrypt-1.0.2.dist-info/METADATA
hashdecrypt-1.0.2.dist-info/RECORD
