Metadata-Version: 2.1
Name: hashdecrypt
Version: 1.0.2
Summary: Decrypt Metamask, Brawe, Ronin, BinanceChain vault data via Python
License: MIT
Author: M16
Requires-Python: >=3.7,<4.0
Classifier: License :: OSI Approved :: MIT License
Classifier: Programming Language :: Python :: 3
Classifier: Programming Language :: Python :: 3.10
Classifier: Programming Language :: Python :: 3.7
Classifier: Programming Language :: Python :: 3.8
Classifier: Programming Language :: Python :: 3.9
Requires-Dist: requests (>=2.1,<3.0)
